missingvals/__init__.py
missingvals/missingvals.py
missingvalsvv3622-0.0.2.dist-info/LICENSE.txt
missingvalsvv3622-0.0.2.dist-info/METADATA
missingvalsvv3622-0.0.2.dist-info/WHEEL
missingvalsvv3622-0.0.2.dist-info/entry_points.txt
missingvalsvv3622-0.0.2.dist-info/top_level.txt
missingvalsvv3622-0.0.2.dist-info/RECORD
