Metadata-Version: 2.1
Name: missingvalsvv3622
Version: 0.0.2
Summary: Use this package to replace missing values in your data by mean of columns
Home-page: 
Author: Vishesh Verma
Author-email: visheshv2001@gmail.com
License: UNKNOWN
Platform: UNKNOWN
Classifier: Programming Language :: Python :: 3
Classifier: License :: OSI Approved :: MIT License
Classifier: Operating System :: OS Independent
